.gitignore
CHANGES.txt
README.txt
development.ini
setup.cfg
setup.py
JoCommentAtom.egg-info/PKG-INFO
JoCommentAtom.egg-info/SOURCES.txt
JoCommentAtom.egg-info/dependency_links.txt
JoCommentAtom.egg-info/entry_points.txt
JoCommentAtom.egg-info/not-zip-safe
JoCommentAtom.egg-info/paster_plugins.txt
JoCommentAtom.egg-info/requires.txt
JoCommentAtom.egg-info/top_level.txt
jocommentatom/__init__.py
jocommentatom/deployment.ini_tmpl
jocommentatom/models.py
jocommentatom/tests.py
jocommentatom/views.py
jocommentatom/lib/__init__.py
jocommentatom/lib/installer.py
jocommentatom/templates/atom_feed.pt