Metadata-Version: 1.0
Name: JoCommentAtom
Version: 0.1.3
Summary: Atom feed generator for JoComment.
Home-page: http://pypi.python.org/pypi/JoCommentAtom
Author: Jakub Warmuz
Author-email: jakub.warmuz@gmail.com
License: UNKNOWN
Keywords: joomla php joomlacomment comment atom feed rss web wsgi bfg pylons pyramid
Platform: UNKNOWN
Classifier: Programming Language :: Python
Classifier: Framework :: Pylons
Classifier: Topic :: Internet :: WWW/HTTP
Classifier: Topic :: Internet :: WWW/HTTP :: WSGI :: Application
